README.md
setup.py
xor_tools/__init__.py
xor_tools/rolling_key.py
xor_tools/xor_encrypt_file.py
xor_tools/xor_key_recovery.py
xor_tools.egg-info/PKG-INFO
xor_tools.egg-info/SOURCES.txt
xor_tools.egg-info/dependency_links.txt
xor_tools.egg-info/entry_points.txt
xor_tools.egg-info/top_level.txt