Metadata-Version: 2.1
Name: xor-tools
Version: 1.0.1
Summary: XOR Tools
Home-page: https://github.com/lukaskuzmiak/xor_tools
Author: Lukas Kuzmiak, nshadov
Author-email: lukash@backstep.net
License: MIT
Keywords: xor key recovery encrypt decrypt
Platform: UNKNOWN
Classifier: Programming Language :: Python :: 3
Classifier: License :: OSI Approved :: MIT License
Classifier: Operating System :: OS Independent
Requires-Python: >3.5.2
